__init__.py
py.py
ENDECODE_VALAZ-0.0.2.dist-info/LICENSE.txt
ENDECODE_VALAZ-0.0.2.dist-info/METADATA
ENDECODE_VALAZ-0.0.2.dist-info/WHEEL
ENDECODE_VALAZ-0.0.2.dist-info/top_level.txt
ENDECODE_VALAZ-0.0.2.dist-info/RECORD
