Metadata-Version: 2.1
Name: ENDECODE_VALAZ
Version: 0.0.2
Summary: Encoder Decoder for Text Tokenization
Author-email: valaz <info@cogitoedge.com>
Project-URL: Homepage, https://github.com/cogitoedge
Project-URL: Issues, https://github.com/cogitoedge
Classifier: Programming Language :: Python :: 3
Classifier: License :: OSI Approved :: MIT License
Classifier: Operating System :: OS Independent
Requires-Python: >=3.10
License-File: LICENSE.txt
